LICENSE
MANIFEST.in
README.rst
setup.py
tests.py
docs/Makefile
docs/api.rst
docs/conf.py
docs/index.rst
docs/_build/doctrees/api.doctree
docs/_build/doctrees/environment.pickle
docs/_build/doctrees/index.doctree
docs/_build/doctrees/_themes/README.doctree
docs/_build/doctrees/user/install.doctree
docs/_build/doctrees/user/intro.doctree
docs/_build/doctrees/user/quickstart.doctree
docs/_build/html/.buildinfo
docs/_build/html/api.html
docs/_build/html/genindex.html
docs/_build/html/index.html
docs/_build/html/objects.inv
docs/_build/html/search.html
docs/_build/html/searchindex.js
docs/_build/html/_sources/api.txt
docs/_build/html/_sources/index.txt
docs/_build/html/_sources/_themes/README.txt
docs/_build/html/_sources/user/install.txt
docs/_build/html/_sources/user/intro.txt
docs/_build/html/_sources/user/quickstart.txt
docs/_build/html/_static/ajax-loader.gif
docs/_build/html/_static/basic.css
docs/_build/html/_static/comment-bright.png
docs/_build/html/_static/comment-close.png
docs/_build/html/_static/comment.png
docs/_build/html/_static/doctools.js
docs/_build/html/_static/down-pressed.png
docs/_build/html/_static/down.png
docs/_build/html/_static/file.png
docs/_build/html/_static/flasky.css
docs/_build/html/_static/jquery.js
docs/_build/html/_static/minus.png
docs/_build/html/_static/plus.png
docs/_build/html/_static/pygments.css
docs/_build/html/_static/rst-sidebar.png
docs/_build/html/_static/searchtools.js
docs/_build/html/_static/small_flask.css
docs/_build/html/_static/underscore.js
docs/_build/html/_static/up-pressed.png
docs/_build/html/_static/up.png
docs/_build/html/_static/websupport.js
docs/_build/html/_themes/README.html
docs/_build/html/user/install.html
docs/_build/html/user/intro.html
docs/_build/html/user/quickstart.html
docs/_static/rst-sidebar.png
docs/_templates/sidebarintro.html
docs/_templates/sidebarlogo.html
docs/_themes/LICENSE
docs/_themes/README.rst
docs/_themes/flask_theme_support.py
docs/_themes/flask_theme_support.pyc
rst.egg-info/PKG-INFO
rst.egg-info/SOURCES.txt
rst.egg-info/dependency_links.txt
rst.egg-info/requires.txt
rst.egg-info/top_level.txt