Metadata-Version: 1.1
Name: rst
Version: 0.1
Summary: Module to create reStructuredText documents through code.
Home-page: http://rst.rtfd.org
Author: Kushal Das
Author-email: kushaldas@gmail.com
License: MIT
Platform: UNKNOWN
Classifier: Development Status :: 4 - Beta
Classifier: Topic :: Software Development :: Libraries
Classifier: License :: OSI Approved :: MIT License
Classifier: Topic :: System :: Distributed Computing
Classifier: Programming Language :: Python :: 2.6
Classifier: Programming Language :: Python :: 2.7
Classifier: Programming Language :: Python :: 3.2
